{
	"Version": 3,
	"Parameters": [
		{
			"Id": "ParamAngleX",
			"GroupId": "ParamGroup",
			"Name": "Angle X"
		},
		{
			"Id": "ParamAngleY",
			"GroupId": "ParamGroup",
			"Name": "Angle Y"
		},
		{
			"Id": "ParamAngleZ",
			"GroupId": "ParamGroup",
			"Name": "Angle Z"
		},
		{
			"Id": "ParamEyeBallX",
			"GroupId": "ParamGroup2",
			"Name": "Eyeball X"
		},
		{
			"Id": "ParamEyeBallY",
			"GroupId": "ParamGroup2",
			"Name": "Eyeball Y"
		},
		{
			"Id": "ParamBrowLY",
			"GroupId": "ParamGroup3",
			"Name": "BrowL Y"
		},
		{
			"Id": "ParamBrowRY",
			"GroupId": "ParamGroup3",
			"Name": "BrowR Y"
		},
		{
			"Id": "ParamBrowLX",
			"GroupId": "ParamGroup3",
			"Name": "BrowL X"
		},
		{
			"Id": "ParamBrowRX",
			"GroupId": "ParamGroup3",
			"Name": "BrowR X"
		},
		{
			"Id": "ParamBrowLAngle",
			"GroupId": "ParamGroup3",
			"Name": "BrowL Angle"
		},
		{
			"Id": "ParamBrowRAngle",
			"GroupId": "ParamGroup3",
			"Name": "BrowR Angle"
		},
		{
			"Id": "ParamBrowLForm",
			"GroupId": "ParamGroup3",
			"Name": "BrowL Form"
		},
		{
			"Id": "ParamBrowRForm",
			"GroupId": "ParamGroup3",
			"Name": "BrowR Form"
		},
		{
			"Id": "ParamMouthOpenY",
			"GroupId": "ParamGroup4",
			"Name": "Mouth Open"
		},
		{
			"Id": "ParamMouthForm",
			"GroupId": "ParamGroup4",
			"Name": "Mouth Form"
		},
		{
			"Id": "ParamEyeLOpen",
			"GroupId": "",
			"Name": "EyeL Open"
		},
		{
			"Id": "ParamEyeLSmile",
			"GroupId": "",
			"Name": "EyeL Smile"
		},
		{
			"Id": "ParamEyeROpen",
			"GroupId": "",
			"Name": "EyeR Open"
		},
		{
			"Id": "ParamEyeRSmile",
			"GroupId": "",
			"Name": "EyeR Smile"
		},
		{
			"Id": "ParamCheek",
			"GroupId": "",
			"Name": "Cheek"
		},
		{
			"Id": "ParamBodyAngleX",
			"GroupId": "",
			"Name": "Body X"
		},
		{
			"Id": "ParamBodyAngleY",
			"GroupId": "",
			"Name": "Body Y"
		},
		{
			"Id": "ParamBodyAngleZ",
			"GroupId": "",
			"Name": "Body Z"
		},
		{
			"Id": "ParamBreath",
			"GroupId": "",
			"Name": "Breath"
		},
		{
			"Id": "ParamHairFront",
			"GroupId": "",
			"Name": "Hair Move Front"
		},
		{
			"Id": "ParamHairSide",
			"GroupId": "",
			"Name": "Hair Move Side"
		},
		{
			"Id": "ParamHairBack",
			"GroupId": "",
			"Name": "Hair Move Back"
		}
	],
	"ParameterGroups": [
		{
			"Id": "ParamGroup",
			"GroupId": "",
			"Name": "Face"
		},
		{
			"Id": "ParamGroup2",
			"GroupId": "",
			"Name": "Eyeball"
		},
		{
			"Id": "ParamGroup3",
			"GroupId": "",
			"Name": "Brow"
		},
		{
			"Id": "ParamGroup4",
			"GroupId": "",
			"Name": "Mouth"
		}
	],
	"Parts": [
		{
			"Id": "Part2",
			"Name": "gumbsona copy 9 separate jacket.psd (Corresponding layer not found)"
		},
		{
			"Id": "Part",
			"Name": "gumbsona copy 7 eyelids.psd (Corresponding layer not found)"
		},
		{
			"Id": "PartRough",
			"Name": "Rough Design"
		},
		{
			"Id": "Part3",
			"Name": "Core"
		},
		{
			"Id": "PartFace",
			"Name": "Face"
		},
		{
			"Id": "PartEye",
			"Name": "Eye"
		},
		{
			"Id": "PartEyeBall",
			"Name": "Eyeball"
		},
		{
			"Id": "PartBrow",
			"Name": "Brows"
		},
		{
			"Id": "PartMouth",
			"Name": "Mouth"
		},
		{
			"Id": "PartNose",
			"Name": "Nose"
		},
		{
			"Id": "PartEar",
			"Name": "Ear"
		},
		{
			"Id": "PartHairFront",
			"Name": "Bangs"
		},
		{
			"Id": "PartHairSide",
			"Name": "Hair Side"
		},
		{
			"Id": "PartHairBack",
			"Name": "Hair Back"
		},
		{
			"Id": "PartNeck",
			"Name": "Neck"
		},
		{
			"Id": "PartBody",
			"Name": "Body"
		},
		{
			"Id": "PartBackground",
			"Name": "Background"
		},
		{
			"Id": "PartSketch",
			"Name": "[ Guide Image]"
		}
	],
	"CombinedParameters": [
		[
			"ParamAngleX",
			"ParamAngleY"
		],
		[
			"ParamMouthOpenY",
			"ParamMouthForm"
		]
	]
}